google_images_download/__init__.py
google_images_download/google_images_download.py
google_images_download-1.0.0.dist-info/DESCRIPTION.rst
google_images_download-1.0.0.dist-info/METADATA
google_images_download-1.0.0.dist-info/RECORD
google_images_download-1.0.0.dist-info/WHEEL
google_images_download-1.0.0.dist-info/entry_points.txt
google_images_download-1.0.0.dist-info/metadata.json
google_images_download-1.0.0.dist-info/top_level.txt
