Metadata-Version: 2.0
Name: google-images-download
Version: 1.0.0
Summary: Python Script to download hundreds of images from 'Google Images'. It is a ready-to-run code! 
Home-page: https://github.com/hardikvasa/google-images-download
Author: Hardik Vasa
Author-email: psuzzn@gmail.com
License: BSD
Download-URL: https://github.com/hardikvasa/google-images-download/tarball/1.0.0
Platform: UNKNOWN
Classifier: Development Status :: 3 - Alpha
Classifier: Intended Audience :: Developers
Classifier: Programming Language :: Python :: 3
